oddoreven/__init__.py
oddoreven/checker.py
oddoreven_samjoseph-0.1.0.dist-info/METADATA
oddoreven_samjoseph-0.1.0.dist-info/WHEEL
oddoreven_samjoseph-0.1.0.dist-info/top_level.txt
oddoreven_samjoseph-0.1.0.dist-info/RECORD
