Metadata-Version: 2.4
Name: oddoreven-samjoseph
Version: 0.1.0
Summary: A simple Python package to check whether a number is odd or even.
Author-email: Sam Joseph <your_email@example.com>
License-Expression: MIT
Project-URL: Homepage, https://pypi.org/project/oddoreven-samjoseph/
Requires-Python: >=3.7
